<?xml version="1.0" ?>
<task isactivity="0" level="56" maxl="61" minl="54" ramus="1" tt="强军（五）" usemoney="0">
    <dt>
        抓捕一些汗血宝马来武装部队。
    </dt>
    <ot>
        <r a="3" q="\t一只好的部队怎可没有坐骑。材料还有不少剩余，我在这里为将军铸造好坐骑鞍套，将军需要尽快弄一批出色的坐骑来，这样才能瞬息千里，打的敌人如五雷轰顶一般战栗。\n\t听说有人在拉萨平原看到过汗血宝马，那种马力大如牛，瞬息千里，连虎豹都退之三舍，正好作为大军的坐骑。"/>
    </ot>
    <et>
        <r a="1" q="\t呼……老夫能帮忙的也就到此为止了，希望将军不要辜负我们广大子民的期望，保卫赞普，保卫我吐蕃大好河山。"/>
    </et>
    <it>
        <r a="2" q="我期待这一只无敌军团的诞生。"/>
    </it>
    <award>
        <exp num="400000"/>
        <money num="3446" type="1"/>
    </award>
    <detail>
        去{拉萨平原,1140001}杀(汗血宝马,1140001)@1，回复(菲特,2130001)
    </detail>
    <anpc>
        2130001
    </anpc>
    <cnpc>
        2130001
    </cnpc>
    <objs>
        <a id="1140001" n="50" name="汗血宝马"/>
    </objs>
    <track_tar>
        去{拉萨平原,1140001}杀(汗血宝马,1140001)@1
    </track_tar>
    <track_comp>
        回复(菲特,2130001)
    </track_comp>
    <otype>
        1
    </otype>
</task>
