<?xml version="1.0" ?>
<task isactivity="0" level="20" maxl="25" minl="18" ramus="1" tt="绞杀内贼" usemoney="0">
    <dt>
        斩杀偷窃了夜明珠的王庭侍卫桑多次杰。
    </dt>
    <ot>
        <r a="3" q="\t桑多次杰竟然连赞普的物品也敢染指，看来这些年的养尊处优已经让他忘记了战士的荣耀，杀！杀无赦，提着他的人头来见我。"/>
    </ot>
    <et>
        <r a="1" q="\t血淋淋的人头啊，桑多次杰，你可记得昔日你我是如何在赞普座下宣誓的，你可记得昔日你我是如何并肩杀敌的，你可记得……别怪哥哥，这一切是你咎由自取！年轻人，这一次你做的不错。"/>
    </et>
    <it>
        <r a="2" q="杀！杀无赦！"/>
    </it>
    <award>
        <exp num="9000"/>
    </award>
    <detail>
        去{甲玛城,1030128}杀(桑多次杰,1030128)，去{甲玛城,2030127}回复(队长班典,2030127)
    </detail>
    <anpc>
        2030127
    </anpc>
    <cnpc>
        2030127
    </cnpc>
    <objs>
        <a id="1030128" n="1" name="桑多次杰"/>
    </objs>
    <track_tar>
        去{甲玛城,1030128}杀(桑多次杰,1030128)
    </track_tar>
    <track_comp>
        去{甲玛城,2030127}回复(队长班典,2030127)
    </track_comp>
    <otype>
        1
    </otype>
</task>
