<?xml version="1.0" ?>
<task isactivity="0" level="31" maxl="99" minl="99" ramus="2" tt="烦恼(二)" usemoney="0">
    <dt>
        为大巫师扎西勒仁收集一些补脑的材料。
    </dt>
    <ot>
        <r a="3" q="\t大巫师是我们的智者，是我们思想的先驱，然而随着他的年纪日益增大，脑袋也远远不如曾经那么清晰。听说猴脑很补，帮我弄些山猴的脑髓，送给大巫师扎西勒仁。"/>
    </ot>
    <et>
        <r a="1" q="\t感谢你，小伙子，同时也代我感谢茹杰梅朵。"/>
    </et>
    <it>
        <r a="2" q="帮我弄些山猴的脑髓，我得帮大巫师制作一副药剂。"/>
    </it>
    <award>
        <exp num="75000"/>
        <money num="728" type="1"/>
    </award>
    <detail>
        去{山猴洞,1060112}获得(山猴的脑髓,1060112)@1，回复(茹杰梅朵,2060001)
    </detail>
    <cnpc>
        2060002
    </cnpc>
    <objs>
        <a id="1060112" n="20" name="山猴的脑髓"/>
    </objs>
    <track_tar>
        去{山猴洞,1060112}获得(山猴的脑髓,1060112)@1
    </track_tar>
    <track_comp>
        回复(茹杰梅朵,2060001)
    </track_comp>
    <otype>
        1
    </otype>
</task>
