<?xml version="1.0" ?>
<task isactivity="0" level="73" maxl="100" minl="100" ramus="1" tt="守护神" usemoney="0">
    <dt>
        带着祖巫的头颅回见松赞干布。
    </dt>
    <ot>
        <r a="3" q="\t这颗祖巫的头颅你带回去交给现在的君主松赞干布吧，希望它能带给世人警醒。未来……也许是个多事之秋啊……许多久远的存在会渐渐苏醒。"/>
    </ot>
    <et>
        <r a="1" q="\t这颗头颅？呼……当传说真正的出现在眼前，这一切便由不得本王怀疑了，将军不愧是我吐蕃的守护神！\n\t即日起本王将秣兵厉马，定当庇护我吐蕃上下子民百世平安。"/>
    </et>
    <it>
        <r a="2" q=""/>
    </it>
    <award>
        <exp num="1250000"/>
        <money num="6200" type="1"/>
    </award>
    <detail>
        返回{拉萨城,2120003}回复(松赞干布,2120003)
    </detail>
    <cnpc>
        2120003
    </cnpc>
    <anpc>
        2160101
    </anpc>
    <objs/>
    <track_tar>
        []
    </track_tar>
    <track_comp>
        返回{拉萨城,2120003}回复(松赞干布,2120003)
    </track_comp>
    <otype>
        1
    </otype>
</task>
