<?xml version="1.0" ?>
<task isactivity="0" level="69" maxl="75" minl="66" ramus="1" tt="氏人盟军" usemoney="0">
    <dt>
        向氏人盟军了解关于落日沼泽的消息。
    </dt>
    <ot>
        <r a="3" q="\t终于肃清了这里的九黎族人，但他们真正的老巢是落日沼泽，在那里我们将面临前所未有的挑战。\n\t落日沼泽原本还存在着一只氏人部落，在九黎族信仰祖巫神教后被打败驱逐。敌人的敌人也就是我们的盟友，所以我们要借助他们的力量，他们对落日沼泽的了解是我们无法比拟的。"/>
    </ot>
    <et>
        <r a="1" q="\t您好，尊贵的大将军，我感受到了您对九黎巫族的满腔杀意，因为我们氏人也是如此。"/>
    </et>
    <it>
        <r a="2" q="敌人的敌人就是我们的朋友，为了击败九黎巫族，我们要善于借势。"/>
    </it>
    <award>
        <exp num="450000"/>
        <money num="4250" type="1"/>
    </award>
    <detail>
        与{暮色边陲,2150003}的(氏人盟军,2150003)交谈
    </detail>
    <anpc>
        2150001
    </anpc>
    <cnpc>
        2150003
    </cnpc>
    <objs/>
    <track_tar>
        []
    </track_tar>
    <track_comp>
        与{暮色边陲,2150003}的(氏人盟军,2150003)交谈
    </track_comp>
    <otype>
        1
    </otype>
</task>
